python_telegram_broadcast/__init__.py
python_telegram_broadcast/custom_dataclass.py
python_telegram_broadcast/custom_exception.py
python_telegram_broadcast/custom_util.py
python_telegram_broadcast/main.py
python_telegram_broadcast/send_method.py
python_telegram_broadcast/strategy.py
python_telegram_broadcast-0.9.7.dist-info/LICENSE
python_telegram_broadcast-0.9.7.dist-info/METADATA
python_telegram_broadcast-0.9.7.dist-info/WHEEL
python_telegram_broadcast-0.9.7.dist-info/top_level.txt
python_telegram_broadcast-0.9.7.dist-info/RECORD
